CHANGES.txt
CONTRIBUTORS.txt
MANIFEST.in
README.txt
setup.cfg
setup.py
docs/HISTORY.txt
docs/INSTALL.txt
docs/LICENSE.GPL
docs/LICENSE.txt
xhostplus/__init__.py
xhostplus.blog.egg-info/PKG-INFO
xhostplus.blog.egg-info/SOURCES.txt
xhostplus.blog.egg-info/dependency_links.txt
xhostplus.blog.egg-info/entry_points.txt
xhostplus.blog.egg-info/namespace_packages.txt
xhostplus.blog.egg-info/not-zip-safe
xhostplus.blog.egg-info/paster_plugins.txt
xhostplus.blog.egg-info/requires.txt
xhostplus.blog.egg-info/top_level.txt
xhostplus/blog/README.txt
xhostplus/blog/__init__.py
xhostplus/blog/config.py
xhostplus/blog/configure.zcml
xhostplus/blog/browser/__init__.py
xhostplus/blog/browser/blog_entry_view.pt
xhostplus/blog/browser/blog_view.pt
xhostplus/blog/browser/blog_view.py
xhostplus/blog/browser/configure.zcml
xhostplus/blog/content/__init__.py
xhostplus/blog/content/blog.py
xhostplus/blog/content/blogentry.py
xhostplus/blog/content/configure.zcml
xhostplus/blog/content/listeners.py
xhostplus/blog/interfaces/__init__.py
xhostplus/blog/interfaces/blog.py
xhostplus/blog/interfaces/blogentry.py
xhostplus/blog/locales/xhostplus.blog.pot
xhostplus/blog/locales/de/LC_MESSAGES/xhostplus.blog.mo
xhostplus/blog/locales/de/LC_MESSAGES/xhostplus.blog.po
xhostplus/blog/locales/en/LC_MESSAGES/xhostplus.blog.mo
xhostplus/blog/locales/en/LC_MESSAGES/xhostplus.blog.po
xhostplus/blog/portlets/__init__.py
xhostplus/blog/portlets/configure.zcml
xhostplus/blog/profiles/default/browserlayer.xml
xhostplus/blog/profiles/default/cssregistry.xml
xhostplus/blog/profiles/default/factorytool.xml
xhostplus/blog/profiles/default/metadata.xml
xhostplus/blog/profiles/default/portlets.xml
xhostplus/blog/profiles/default/rolemap.xml
xhostplus/blog/profiles/default/skins.xml
xhostplus/blog/profiles/default/types.xml
xhostplus/blog/profiles/default/types/Blog.xml
xhostplus/blog/profiles/default/types/Blog_Entry.xml
xhostplus/blog/skins/xhostplus_blog_images/empty
xhostplus/blog/skins/xhostplus_blog_images/xhostplus_blog_icon.png
xhostplus/blog/skins/xhostplus_blog_javascripts/empty
xhostplus/blog/skins/xhostplus_blog_styles/xhostplus_blog.css
xhostplus/blog/skins/xhostplus_blog_templates/xhostplus_blog_macros.pt
xhostplus/blog/tests/__init__.py
xhostplus/blog/tests/base.py
xhostplus/blog/tests/test_doctest.py