Metadata-Version: 1.1
Name: xhostplus.blog
Version: 1.0.1
Summary: XHOSTPLUS Blog Product for Plone 4
Home-page: http://www.xhostplus.at/de/services/plone-downlods
Author: UNKNOWN
Author-email: UNKNOWN
License: GPL
Platform: UNKNOWN
Classifier: Framework :: Plone
Classifier: Intended Audience :: Developers
Classifier: License :: OSI Approved :: GNU General Public License (GPL)
